bogs/__init__.py
bogs/damageprob/DamageProbability.py
bogs/damageprob/__init__.py
bogs/damageprob/probplot.py
bogs/functionality/Functionality.py
bogs/functionality/__init__.py
bogs/hazard/Cyclone.py
bogs/hazard/__init__.py
bogs/loss/__init__.py
bogs/loss/cost.py
bogs/plot/__init__.py
bogs/plot/mapplot.py
bogs/recovery/__init__.py
bogs/recovery/recovery.py
bogs/social/__init__.py
bogs/social/socialanalysis.py
bogs/vulnerability/DR.py
bogs/vulnerability/Fragility.py
bogs/vulnerability/Vulnerability.py
bogs/vulnerability/__init__.py
bogs-0.1.10.dist-info/LICENSE
bogs-0.1.10.dist-info/METADATA
bogs-0.1.10.dist-info/WHEEL
bogs-0.1.10.dist-info/top_level.txt
bogs-0.1.10.dist-info/RECORD
