Metadata-Version: 2.1
Name: bogs
Version: 0.1.10
Summary: A short description of your project
Home-page: https://github.com/Swaran66/TCRA_SRN
Author: Your Name
Author-email: Your Name <your_email@example.com>
License: MIT License
Requires-Python: >=3.6
License-File: LICENSE
Requires-Dist: numpy>=1.21.0
Requires-Dist: matplotlib>=3.4.0
Requires-Dist: pandas>=1.3.0
Requires-Dist: scipy>=1.7.0
Requires-Dist: folium>=0.12.0
